rnc/__init__.py
rnc/corpora.py
rnc/corpora.pyi
rnc/corpora_params.py
rnc/corpora_requests.py
rnc/examples.py
rnc/examples.pyi
rnc-0.10.0.dist-info/LICENSE
rnc-0.10.0.dist-info/WHEEL
rnc-0.10.0.dist-info/METADATA
rnc-0.10.0.dist-info/RECORD
